{
   "contents":[
         {
            "address":"Худ 11-р хороо",
            "caseName": "Хулгай",
            "company":"Нанар ХХК",
            "date":"2020.01.09",
            "email":"bolorchimeg@gmail.com",
            "id":"1",
            "name":"Болорчимэг",
            "payment": "300$",
            "paymentStatus":"Төлөгдөөгүй",
            "phone":"1009990",
            "status":"open",
            "title":"захирал",
            "type":"Хулгай",
            "where":"СБД 3 хороо"            
         },
         {
            "address":"Худ 11-р хороо",
            "caseName": "Хулгай",
            "company":"Ар ХХК",
            "date":"2020.01.09",
            "email":"anar@gmail.com",
            "id":"2",
            "name":"Анар",
            "payment": "500$",
            "paymentStatus":"Төлөгдөөгүй",
            "phone":"1009990",
            "status":"open",
            "title":"захирал",
            "type":"Хулгай",
            "where":"СБД 3 хороо"            
         },
         {
            "address":"Худ 11-р хороо",
            "caseName": "Хулгай",
            "company":"Дорж ХХК",
            "date":"2020.01.09",
            "email":"dorj@gmail.com",
            "id":"3",
            "name":"Болорчимэг",
            "payment": "800$",
            "paymentStatus":"Төлөгдөөгүй",
            "phone":"1009990",
            "status":"open",
            "title":"захирал",
            "type":"Салалт",
            "where":"СБД 3 хороо"            
         },
         {
            "address":"Худ 11-р хороо",
            "caseName": "Хулгай",
            "company":"Өн ХХК",
            "date":"2020.01.09",
            "email":"оdmaa@gmail.com",
            "id":"4",
            "name":"Одмаа",
            "payment": "300$",
            "paymentStatus":"Төлөгдсөн",
            "phone":"1009990",
            "status":"open",
            "title":"захирал",
            "type":"Хулгай",
            "where":"СБД 3 хороо"            
         },
         {
            "address":"Худ 11-р хороо",
            "caseName": "Хулгай",
            "company":"сонор ХХК",
            "date":"2020.01.09",
            "email":"ankhmaag@gmail.com",
            "id":"5",
            "name":"Анхмаа",
            "payment": "800$",
            "paymentStatus":"Төлөгдсөн",
            "phone":"9909990",
            "status":"close",
            "title":"захирал",
            "type":"салалт",
            "where":"СБД 3 хороо"            
         },
         {
            "address":"Худ 11-р хороо",
            "caseName": "Хулгай",
            "company":"Нанар ХХК",
            "date":"2020.01.09",
            "email":"bolorchimeg@gmail.com",
            "id":"6",
            "name":"Төр",
            "payment": "300$",
            "paymentStatus":"Төлөгдөөгүй",
            "phone":"8809990",
            "status":"open",
            "title":"захирал",
            "type":"Хулгай",
            "where":"СБД 3 хороо"            
         },
         {
            "address":"Худ 11-р хороо",
            "caseName": "Хулгай",
            "company":"Нанар ХХК",
            "date":"2020.01.09",
            "email":"bolorchimeg@gmail.com",
            "id":"7",
            "name":"Мөнх",
            "payment": "300$",
            "paymentStatus":"Төлөгдөөгүй",
            "phone":"99119990",
            "status":"open",
            "title":"захирал",
            "type":"Хулгай",
            "where":"СБД 3 хороо"            
         },
         {
            "address":"Худ 11-р хороо",
            "caseName": "Хулгай",
            "company":"Нанар ХХК",
            "date":"2020.01.09",
            "email":"bolorchimeg@gmail.com",
            "id":"1",
            "name":"Болорчимэг",
            "payment": "300$",
            "paymentStatus":"Төлөгдөөгүй",
            "phone":"1009990",
            "status":"open",
            "title":"захирал",
            "type":"Хулгай",
            "where":"СБД 3 хороо"            
         },
         {
            "address":"Худ 11-р хороо",
            "caseName": "Хулгай",
            "company":"Нанар ХХК",
            "date":"2020.01.09",
            "email":"bolorchimeg@gmail.com",
            "id":"1",
            "name":"Болорчимэг",
            "payment": "300$",
            "paymentStatus":"Төлөгдөөгүй",
            "phone":"1009990",
            "status":"open",
            "title":"захирал",
            "type":"Хулгай",
            "where":"СБД 3 хороо"            
         },
         {
            "address":"Худ 11-р хороо",
            "caseName": "Хулгай",
            "company":"Нанар ХХК",
            "date":"2020.01.09",
            "email":"bolorchimeg@gmail.com",
            "id":"1",
            "name":"Болорчимэг",
            "payment": "300$",
            "paymentStatus":"Төлөгдөөгүй",
            "phone":"1009990",
            "status":"open",
            "title":"захирал",
            "type":"Хулгай",
            "where":"СБД 3 хороо"            
         },
         {
            "address":"Худ 11-р хороо",
            "caseName": "Хулгай",
            "company":"Нанар ХХК",
            "date":"2020.01.09",
            "email":"bolorchimeg@gmail.com",
            "id":"1",
            "name":"Болорчимэг",
            "payment": "300$",
            "paymentStatus":"Төлөгдөөгүй",
            "phone":"1009990",
            "status":"open",
            "title":"захирал",
            "type":"Хулгай",
            "where":"СБД 3 хороо"            
         },
         {
            "address":"Худ 11-р хороо",
            "caseName": "Хулгай",
            "company":"Нанар ХХК",
            "date":"2020.01.09",
            "email":"bolorchimeg@gmail.com",
            "id":"1",
            "name":"Болорчимэг",
            "payment": "300$",
            "paymentStatus":"Төлөгдөөгүй",
            "phone":"1009990",
            "status":"open",
            "title":"захирал",
            "type":"Хулгай",
            "where":"СБД 3 хороо"            
         },
         {
            "address":"Худ 11-р хороо",
            "caseName": "Хулгай",
            "company":"Нанар ХХК",
            "date":"2020.01.09",
            "email":"bolorchimeg@gmail.com",
            "id":"1",
            "name":"Болорчимэг",
            "payment": "300$",
            "paymentStatus":"Төлөгдөөгүй",
            "phone":"1009990",
            "status":"open",
            "title":"захирал",
            "type":"Хулгай",
            "where":"СБД 3 хороо"            
         },
         {
            "address":"Худ 11-р хороо",
            "caseName": "Хулгай",
            "company":"Нанар ХХК",
            "date":"2020.01.09",
            "email":"bolorchimeg@gmail.com",
            "id":"1",
            "name":"Болорчимэг",
            "payment": "300$",
            "paymentStatus":"Төлөгдөөгүй",
            "phone":"1009990",
            "status":"open",
            "title":"захирал",
            "type":"Хулгай",
            "where":"СБД 3 хороо"            
         },
         {
            "address":"Худ 11-р хороо",
            "caseName": "Хулгай",
            "company":"Нанар ХХК",
            "date":"2020.01.09",
            "email":"bolorchimeg@gmail.com",
            "id":"1",
            "name":"Болорчимэг",
            "payment": "300$",
            "paymentStatus":"Төлөгдөөгүй",
            "phone":"1009990",
            "status":"open",
            "title":"захирал",
            "type":"Хулгай",
            "where":"СБД 3 хороо"            
         },
         {
            "address":"Худ 11-р хороо",
            "caseName": "Хулгай",
            "company":"Нанар ХХК",
            "date":"2020.01.09",
            "email":"bolorchimeg@gmail.com",
            "id":"1",
            "name":"Болорчимэг",
            "payment": "300$",
            "paymentStatus":"Төлөгдөөгүй",
            "phone":"1009990",
            "status":"open",
            "title":"захирал",
            "type":"Хулгай",
            "where":"СБД 3 хороо"            
         },

         {
            "address":"Худ 11-р хороо",
            "caseName": "Хулгай",
            "company":"Нанар ХХК",
            "date":"2020.01.09",
            "email":"bolorchimeg@gmail.com",
            "id":"1",
            "name":"Болорчимэг",
            "payment": "300$",
            "paymentStatus":"Төлөгдөөгүй",
            "phone":"1009990",
            "status":"open",
            "title":"захирал",
            "type":"Хулгай",
            "where":"СБД 3 хороо"            
         }
   ],
   
      "details": [
              {"birthDay" : "1990.01.24", "driverIDname" : "000678", "emergencyName" : "Бат", "emergencyPhone" : "88654321", "marital" : "Гэрлэсэн", "sex" : "Эрэгтэй", "who" : "Эхнэр"},
              {"birthDay" : "1978.01.24", "driverIDname" : "000178", "emergencyName" : "Болд", "emergencyPhone" : "99654321", "marital" : "Ганц бие", "sex" : "Эмэгтэй", "who" : "Нөхөр"},
              {"birthDay" : "1989.11.24", "driverIDname" : "000675", "emergencyName" : "Батдорж", "emergencyPhone" : "87654321", "marital" : "Гэрлэсэн", "sex" : "Эрэгтэй", "who" : "Эхнэр"},
              {"birthDay" : "1990.12.10", "driverIDname" : "000672", "emergencyName" : "Очир", "emergencyPhone" : "86654321", "marital" : "Салсан", "sex" : "Эмэгтэй", "who" : "Нөхөр"},
              {"birthDay" : "1990.02.24", "driverIDname" : "000478", "emergencyName" : "Одмаа", "emergencyPhone" : "98654321", "marital" : "Ганц бие", "sex" : "Эрэгтэй", "who" : "Эхнэр"},
              {"birthDay" : "1990.04.24", "driverIDname" : "000178", "emergencyName" : "Энхмаа", "emergencyPhone" : "99954321", "marital" : "Салсан", "sex" : "Эмэгтэй", "who" : "Нөхөр"},
              {"birthDay" : "1990.07.26", "driverIDname" : "000078", "emergencyName" : "Өнөр", "emergencyPhone" : "88604321", "marital" : "Гэрлэсэн", "sex" : "Эрэгтэй", "who" : "Эхнэр"},
              {"birthDay" : "1990.09.23", "driverIDname" : "000378", "emergencyName" : "Жаргал", "emergencyPhone" : "88654300", "marital" : "Ганц бие", "sex" : "Эмэгтэй", "who" : "Нөхөр"},
              {"birthDay" : "1990.01.20", "driverIDname" : "000478", "emergencyName" : "Шар", "emergencyPhone" : "88650021", "marital" : "Гэрлэсэн", "sex" : "Эрэгтэй", "who" : "Эхнэр"},
              {"birthDay" : "1990.01.05", "driverIDname" : "000678", "emergencyName" : "Анхаа", "emergencyPhone" : "88114321", "marital" : "Салсан", "sex" : "Эмэгтэй", "who" : "Нөхөр"},
              {"birthDay" : "1994.10.13", "driverIDname" : "000458", "emergencyName" : "Жамц", "emergencyPhone" : "99114321", "marital" : "Ганц бие", "sex" : "Эрэгтэй", "who" : "Эхнэр"},
              {"birthDay" : "1990.09.22", "driverIDname" : "000978", "emergencyName" : "Дорж", "emergencyPhone" : "88604321", "marital" : "Гэрлэсэн", "sex" : "Эмэгтэй", "who" : "Нөхөр"},
              {"birthDay" : "1989.07.24", "driverIDname" : "000878", "emergencyName" : "Ган", "emergencyPhone" : "96654321", "marital" : "Ганц бие", "sex" : "Эрэгтэй", "who" : "Эхнэр"},
              {"birthDay" : "1967.05.24", "driverIDname" : "000778", "emergencyName" : "Сүх", "emergencyPhone" : "81654321", "marital" : "Салсан", "sex" : "Эрэгтэй", "who" : "Эхнэр"},
              {"birthDay" : "1973.01.24", "driverIDname" : "000278", "emergencyName" : "Анар", "emergencyPhone" : "98114321", "marital" : "Гэрлэсэн", "sex" : "Эмэгтэй", "who" : "Нөхөр"},
              {"birthDay" : "1990.01.24", "driverIDname" : "000678", "emergencyName" : "Бат", "emergencyPhone" : "81114321", "marital" : "Гэрлэсэн", "sex" : "Эмэгтэй", "who" : "Нөхөр"}
          ]
      
}